littleworkers.py
littleworkers-0.3.2.dist-info/DESCRIPTION.rst
littleworkers-0.3.2.dist-info/METADATA
littleworkers-0.3.2.dist-info/pydist.json
littleworkers-0.3.2.dist-info/RECORD
littleworkers-0.3.2.dist-info/top_level.txt
littleworkers-0.3.2.dist-info/WHEEL
