Metadata-Version: 2.0
Name: littleworkers
Version: 0.3.2
Summary: Little process-based workers to do your bidding.
Home-page: https://github.com/toastdriven/littleworkers
Author: Daniel Lindsley
Author-email: daniel@toastdriven.com
License: UNKNOWN
Platform: UNKNOWN
Classifier: Development Status :: 5 - Production/Stable
Classifier: Intended Audience :: Developers
Classifier: License :: OSI Approved :: BSD License
Classifier: Operating System :: OS Independent
Classifier: Programming Language :: Python
Classifier: Topic :: Utilities
